prisma_sdk/__init__.py
prisma_sdk/client.py
prisma_sdk-0.0.5.dist-info/licenses/LICENSE
prisma_sdk-0.0.5.dist-info/METADATA
prisma_sdk-0.0.5.dist-info/WHEEL
prisma_sdk-0.0.5.dist-info/top_level.txt
prisma_sdk-0.0.5.dist-info/RECORD
