Metadata-Version: 2.4
Name: prisma-sdk
Version: 0.0.5
Summary: A simple Python SDK for interacting with the Prisma API.
Author-email: GS <gianluscibi98@gmail.com>
License: MIT
Project-URL: Homepage, https://github.com/gscibi/prisma_sdk
Requires-Python: >=3.8
License-File: LICENSE
Requires-Dist: requests>=2.28.0
Dynamic: license-file
